FSM/rtl/top.v
// RTL coding for module detect  the 1011 string
module string_detector #(parameter FSM_MEALY = 1) (
	input wire clk,
	input wire rst_n,
	input wire din,
	output reg match
);

reg [2:0] state, next_state;

// State encoding
localparam IDLE = 3'b000;
localparam S1 = 3'b001;
localparam S10 = 3'b010;
localparam S101 = 3'b011;
localparam S1011 = 3'b100;

// State transition
always @(posedge clk or negedge rst_n) begin
	if (!rst_n) begin
		state <= IDLE;
	end else begin
		state <= next_state;
	end
end
// Next state logic
always @(*) begin
	case (state)
		IDLE: next_state = din ? S1 : IDLE;
		S1: next_state = din ? S1 : S10;
		S10: next_state = din ? S101 : IDLE;
		S101: next_state = din ? S1011 : S10;
		S1011: next_state = din ? S1 : S10;
		default: next_state = IDLE;
	endcase
end

// output logic
always @(*) begin
	if (!rst_n) begin 
		match <= 1'b0;
	end else if (FSM_MEALY) begin
		match <= (state == S101 && din);
	end else begin
		match <= (state == S1011);
	end
end
endmodule

FSM/tb/test_bench.v
`timescale 1ns/1ps
module test_bench;
	reg clk;
	reg rst_n;
	reg din;
	wire match;

parameter FSM_MEALY = 1;

string_detector #(FSM_MEALY) dut(
	.clk(clk),
	.rst_n(rst_n),
	.din(din),
	.match(match)
);

	task verify;
		input exp_match;
		begin
			$display("At time: %t, rst_n = 1'b%b", $time, rst_n);
			if (match == exp_match) begin
				$display("---------------------------------------------------------------------------------------------------------------------------");
				$display("PASSED: Expected match: 1'b%b, Got match: 1'b%b", exp_match, match);
				$display("---------------------------------------------------------------------------------------------------------------------------");
			end else begin
				$display("---------------------------------------------------------------------------------------------------------------------------");
				$display("FAILED: Expected match: 1'b%b, Got match: 1'b%b", exp_match, match);
				$display("---------------------------------------------------------------------------------------------------------------------------");
			end
		end
	endtask

	initial begin
		clk = 0;
		forever #5 clk = ~clk;
	end
		
	initial begin
		$dumpfile("test_bench.vcd");
		$dumpvars(0, test_bench);

		$display("---------------------------------------------------------------------------------------------------------------------------");
		$display("---------------------------------------------TESTBECNH FOR STRING DETECTOR-------------------------------------------------");
		$display("---------------------------------------------------------------------------------------------------------------------------");

		rst_n = 0;
		din = 0;
		@(posedge clk);
		verify(0);

		// Detecting string "101011011001011"
		rst_n = 1;
		din = 1;
		@(posedge clk);  // 1
		din = 0;
		@(posedge clk);  // 10
		verify(0);
		din = 1;
		@(posedge clk);  // 101
		din = 0;
		@(posedge clk);  // 10
		verify(0);
		din = 1;
		@(posedge clk); // 101
		verify(0);
		din = 1;
		@(posedge clk); // 1011
		verify(1);
		din = 0;
		@(posedge clk); // 10
		verify(0);
		din = 1;
		@(posedge clk); // 101
		verify(0);
		din = 1;
		@(posedge clk); // 1011
		verify(1);
		din = 0;
		@(posedge clk); // 10
		din = 0;
		@(posedge clk); // 0
		verify(0);
		din = 1;
		@(posedge clk) // 1;
		din = 0;
		@(posedge clk); // 10;
		din = 1;
		@(posedge clk); // 101;
		verify(0);
		din = 1;
		@(posedge clk); // 1011
		verify(1);

		#1;
		$finish;
	end
endmodule

FSM/sim/test_bench.vcd
$date
	Fri Jan 10 10:57:34 2025
$end
$version
	Icarus Verilog
$end
$timescale
	1ps
$end
$scope module test_bench $end
$var wire 1 ! match $end
$var parameter 32 " FSM_MEALY $end
$var reg 1 # clk $end
$var reg 1 $ din $end
$var reg 1 % rst_n $end
$scope module dut $end
$var wire 1 # clk $end
$var wire 1 $ din $end
$var wire 1 % rst_n $end
$var parameter 32 & FSM_MEALY $end
$var parameter 3 ' IDLE $end
$var parameter 3 ( S1 $end
$var parameter 3 ) S10 $end
$var parameter 3 * S101 $end
$var parameter 3 + S1011 $end
$var reg 1 ! match $end
$var reg 3 , next_state [2:0] $end
$var reg 3 - state [2:0] $end
$upscope $end
$scope task verify $end
$var reg 1 . exp_match $end
$upscope $end
$upscope $end
$enddefinitions $end
$comment Show the parameter values. $end
$dumpall
b100 +
b11 *
b10 )
b1 (
b0 '
b1 &
b1 "
$end
#0
$dumpvars
x.
b0 -
b0 ,
0%
0$
0#
0!
$end
#5000
b1 ,
1$
1%
0.
1#
#10000
0#
#15000
b1 -
b10 ,
0$
1#
#20000
0#
#25000
b10 -
b11 ,
1$
1#
#30000
0#
#35000
b11 -
b10 ,
0$
1#
#40000
0#
#45000
0!
b10 -
b11 ,
1$
1#
#50000
0#
#55000
1!
b100 ,
b11 -
1#
#60000
0#
#65000
0!
b100 -
b10 ,
0$
1.
1#
#70000
0#
#75000
b10 -
b11 ,
1$
0.
1#
#80000
0#
#85000
1!
b100 ,
b11 -
1#
#90000
0#
#95000
0!
b100 -
b10 ,
0$
1.
1#
#100000
0#
#105000
b0 ,
b10 -
1#
#110000
0#
#115000
b0 -
b1 ,
1$
0.
1#
#120000
0#
#125000
b1 -
b10 ,
0$
1#
#130000
0#
#135000
b10 -
b11 ,
1$
1#
#140000
0#
#145000
1!
b100 ,
b11 -
1#
#150000
0#
#155000
0!
b1 ,
b100 -
1.
1#
